genetics/__init__.py
genetics/__main__.py
genetics/api/__init__.py
genetics/api/applyPatches.py
genetics/api/genPatches.py
genetics/api/genSources.py
genetics/helpers/__init__.py
genetics/helpers/git.py
breadcord_genetics-0.2.2.dist-info/LICENSE
breadcord_genetics-0.2.2.dist-info/METADATA
breadcord_genetics-0.2.2.dist-info/WHEEL
breadcord_genetics-0.2.2.dist-info/top_level.txt
breadcord_genetics-0.2.2.dist-info/RECORD
